pytest_salt_factories-1.0.5.dist-info/licenses/LICENSE
saltfactories/__init__.py
saltfactories/__main__.py
saltfactories/bases.py
saltfactories/client.py
saltfactories/exceptions.py
saltfactories/manager.py
saltfactories/version.py
saltfactories/cli/__init__.py
saltfactories/cli/call.py
saltfactories/cli/cloud.py
saltfactories/cli/cp.py
saltfactories/cli/key.py
saltfactories/cli/run.py
saltfactories/cli/salt.py
saltfactories/cli/spm.py
saltfactories/cli/ssh.py
saltfactories/daemons/__init__.py
saltfactories/daemons/api.py
saltfactories/daemons/container.py
saltfactories/daemons/master.py
saltfactories/daemons/minion.py
saltfactories/daemons/proxy.py
saltfactories/daemons/sshd.py
saltfactories/daemons/syndic.py
saltfactories/plugins/__init__.py
saltfactories/plugins/event_listener.py
saltfactories/plugins/factories.py
saltfactories/plugins/loader.py
saltfactories/plugins/log_server.py
saltfactories/plugins/markers.py
saltfactories/plugins/sysinfo.py
saltfactories/utils/__init__.py
saltfactories/utils/cli_scripts.py
saltfactories/utils/functional.py
saltfactories/utils/loader.py
saltfactories/utils/markers.py
saltfactories/utils/ports.py
saltfactories/utils/ports.pyi
saltfactories/utils/processes.py
saltfactories/utils/processes.pyi
saltfactories/utils/tempfiles.py
saltfactories/utils/virtualenv.py
saltfactories/utils/coverage/sitecustomize.py
saltfactories/utils/saltext/__init__.py
saltfactories/utils/saltext/engines/__init__.py
saltfactories/utils/saltext/engines/pytest_engine.py
saltfactories/utils/saltext/log_handlers/__init__.py
saltfactories/utils/saltext/log_handlers/pytest_log_handler.py
pytest_salt_factories-1.0.5.dist-info/METADATA
pytest_salt_factories-1.0.5.dist-info/WHEEL
pytest_salt_factories-1.0.5.dist-info/entry_points.txt
pytest_salt_factories-1.0.5.dist-info/top_level.txt
pytest_salt_factories-1.0.5.dist-info/RECORD
