Metadata-Version: 2.4
Name: pytest-salt-factories
Version: 1.0.5
Summary: Pytest Salt Plugin
Home-page: https://github.com/saltstack/pytest-salt-factories
Author: Pedro Algarvio
Author-email: pedro@algarvio.me
License: Apache Software License 2.0
Project-URL: Source, https://github.com/saltstack/pytest-salt-factories
Project-URL: Tracker, https://github.com/saltstack/pytest-salt-factories/issues
Project-URL: Documentation, https://pytest-salt-factories.readthedocs.io
Platform: unix
Platform: linux
Platform: osx
Platform: cygwin
Platform: win32
Classifier: Programming Language :: Python
Classifier: Programming Language :: Cython
Classifier: Programming Language :: Python :: 3
Classifier: Programming Language :: Python :: 3 :: Only
Classifier: Programming Language :: Python :: 3.7
Classifier: Programming Language :: Python :: 3.8
Classifier: Programming Language :: Python :: 3.9
Classifier: Programming Language :: Python :: 3.10
Classifier: Programming Language :: Python :: 3.11
Classifier: Development Status :: 5 - Production/Stable
Classifier: Intended Audience :: Developers
Classifier: License :: OSI Approved :: Apache Software License
Requires-Python: >=3.7
License-File: LICENSE
Requires-Dist: pytest>=7.4.0
Requires-Dist: attrs>=22.2.0
Requires-Dist: pytest-helpers-namespace>=2021.12.29
Requires-Dist: pytest-skip-markers>=1.5.2
Requires-Dist: pytest-system-statistics>=1.0.2
Requires-Dist: pytest-shell-utilities>=1.4.0
Requires-Dist: psutil
Requires-Dist: pyyaml
Requires-Dist: pyzmq
Requires-Dist: msgpack>=0.5.2
Requires-Dist: virtualenv
Provides-Extra: docker
Requires-Dist: docker>=4.0.0; extra == "docker"
Provides-Extra: salt
Requires-Dist: salt>=3005; extra == "salt"
Provides-Extra: docs
Requires-Dist: furo; extra == "docs"
Requires-Dist: sphinx; extra == "docs"
Requires-Dist: sphinx-copybutton; extra == "docs"
Requires-Dist: sphinx-prompt; extra == "docs"
Requires-Dist: sphinxcontrib-spelling; extra == "docs"
Requires-Dist: sphinxcontrib-towncrier>=0.2.1a0; extra == "docs"
Provides-Extra: lint
Requires-Dist: pylint==3.0.3; extra == "lint"
Requires-Dist: pyenchant; extra == "lint"
Requires-Dist: black; python_version >= "3.7" and extra == "lint"
Requires-Dist: reorder-python-imports; python_version >= "3.7" and extra == "lint"
Provides-Extra: tests
Requires-Dist: docker>=4.0.0; extra == "tests"
Requires-Dist: pytest-subtests; extra == "tests"
Requires-Dist: pyfakefs; extra == "tests"
Requires-Dist: importlib-metadata; extra == "tests"
Provides-Extra: changelog
Requires-Dist: towncrier==21.9.0rc1; extra == "changelog"
Dynamic: license-file
Dynamic: provides-extra
Dynamic: requires-dist
